drata_python_api_client/__init__.py
drata_python_api_client/api/__init__.py
drata_python_api_client/api/assets/__init__.py
drata_python_api_client/api/assets/assets_public_controller_create_asset.py
drata_python_api_client/api/assets/assets_public_controller_delete_asset.py
drata_python_api_client/api/assets/assets_public_controller_list_assets.py
drata_python_api_client/api/autopilot/__init__.py
drata_python_api_client/api/autopilot/autopilot_public_controller_retest.py
drata_python_api_client/api/background_check/__init__.py
drata_python_api_client/api/background_check/background_check_public_controller_update_background_check.py
drata_python_api_client/api/companies/__init__.py
drata_python_api_client/api/companies/companies_public_controller_get_company.py
drata_python_api_client/api/connections/__init__.py
drata_python_api_client/api/connections/connections_public_controller_create_idp_connection_with_csv_file.py
drata_python_api_client/api/connections/connections_public_controller_create_idp_connection_with_json_file.py
drata_python_api_client/api/connections/connections_public_controller_get_connections.py
drata_python_api_client/api/connections/connections_public_controller_update_idp_connection_with_csv_file.py
drata_python_api_client/api/connections/connections_public_controller_update_idp_connection_with_json_file.py
drata_python_api_client/api/controls/__init__.py
drata_python_api_client/api/controls/grc_public_controller_bulk_delete_control_owners.py
drata_python_api_client/api/controls/grc_public_controller_create_control.py
drata_python_api_client/api/controls/grc_public_controller_create_control_note.py
drata_python_api_client/api/controls/grc_public_controller_delete_evidence.py
drata_python_api_client/api/controls/grc_public_controller_delete_note.py
drata_python_api_client/api/controls/grc_public_controller_edit_control.py
drata_python_api_client/api/controls/grc_public_controller_get_control_by_id.py
drata_python_api_client-1.1.4.dist-info/LICENSE
drata_python_api_client-1.1.4.dist-info/METADATA
drata_python_api_client-1.1.4.dist-info/WHEEL
drata_python_api_client-1.1.4.dist-info/RECORD
