Metadata-Version: 2.3
Name: drata-python-api-client
Version: 1.1.4
Summary: A client library for accessing Drata's open API
Requires-Python: >=3.9,<4.0
Classifier: Programming Language :: Python :: 3
Classifier: Programming Language :: Python :: 3.9
Classifier: Programming Language :: Python :: 3.10
Classifier: Programming Language :: Python :: 3.11
Classifier: Programming Language :: Python :: 3.12
Classifier: Programming Language :: Python :: 3.13
Requires-Dist: attrs (>=22.2.0)
Requires-Dist: httpx (>=0.20.0,<0.29.0)
Requires-Dist: python-dateutil (>=2.8.0,<3.0.0)
